django_fido/__init__.py
django_fido/apps.py
django_fido/backends.py
django_fido/constants.py
django_fido/forms.py
django_fido/models.py
django_fido/py.typed
django_fido/settings.py
django_fido/urls.py
django_fido/views.py
django_fido/__pycache__/__init__.cpython-310.pyc
django_fido/__pycache__/__init__.cpython-311.pyc
django_fido/__pycache__/__init__.cpython-36.pyc
django_fido/__pycache__/__init__.cpython-38.pyc
django_fido/__pycache__/__init__.cpython-39.pyc
django_fido/__pycache__/apps.cpython-310.pyc
django_fido/__pycache__/apps.cpython-311.pyc
django_fido/__pycache__/apps.cpython-38.pyc
django_fido/__pycache__/apps.cpython-39.pyc
django_fido/__pycache__/backends.cpython-310.pyc
django_fido/__pycache__/backends.cpython-311.pyc
django_fido/__pycache__/backends.cpython-36.pyc
django_fido/__pycache__/backends.cpython-38.pyc
django_fido/__pycache__/backends.cpython-39.pyc
django_fido/__pycache__/constants.cpython-310.pyc
django_fido/__pycache__/constants.cpython-311.pyc
django_fido/__pycache__/constants.cpython-36.pyc
django_fido/__pycache__/constants.cpython-38.pyc
django_fido/__pycache__/constants.cpython-39.pyc
django_fido/__pycache__/forms.cpython-310.pyc
django_fido/__pycache__/forms.cpython-311.pyc
django_fido/__pycache__/forms.cpython-36.pyc
django_fido/__pycache__/forms.cpython-38.pyc
django_fido/__pycache__/forms.cpython-39.pyc
django_fido/__pycache__/models.cpython-310.pyc
django_fido/__pycache__/models.cpython-311.pyc
django_fido/__pycache__/models.cpython-36.pyc
django_fido/__pycache__/models.cpython-38.pyc
django_fido/__pycache__/models.cpython-39.pyc
django_fido/__pycache__/settings.cpython-310.pyc
django_fido/__pycache__/settings.cpython-311.pyc
django_fido/__pycache__/settings.cpython-36.pyc
django_fido/__pycache__/settings.cpython-38.pyc
django_fido/__pycache__/settings.cpython-39.pyc
django_fido/__pycache__/shims.cpython-38.pyc
django_fido/__pycache__/shims.cpython-39.pyc
django_fido/__pycache__/urls.cpython-36.pyc
django_fido-1.2.1.dist-info/LICENSE
django_fido-1.2.1.dist-info/METADATA
django_fido-1.2.1.dist-info/WHEEL
django_fido-1.2.1.dist-info/top_level.txt
django_fido-1.2.1.dist-info/RECORD
