Metadata-Version: 2.1
Name: django-fido
Version: 1.2.1
Summary: Django application for FIDO protocol
Home-page: https://github.com/CZ-NIC/django-fido
Author: Vlastimil Zíma
Author-email: vlastimil.zima@nic.cz
Keywords: django,fido,u2f,fido2
Classifier: Development Status :: 4 - Beta
Classifier: License :: OSI Approved :: MIT License
Classifier: Framework :: Django
Classifier: Framework :: Django :: 3.0
Classifier: Framework :: Django :: 3.1
Classifier: Framework :: Django :: 3.2
Classifier: Framework :: Django :: 4.0
Classifier: Intended Audience :: Developers
Classifier: License :: OSI Approved :: GNU General Public License v3 or later (GPLv3+)
Classifier: Operating System :: OS Independent
Classifier: Programming Language :: Python
Classifier: Programming Language :: Python :: 3
Classifier: Programming Language :: Python :: 3.7
Classifier: Programming Language :: Python :: 3.8
Classifier: Programming Language :: Python :: 3.9
Classifier: Programming Language :: Python :: 3.10
Classifier: Topic :: Internet :: WWW/HTTP
Classifier: Topic :: Security :: Cryptography
Classifier: Topic :: Software Development :: Libraries :: Python Modules
Requires-Python: ~=3.7
Provides-Extra: quality
Provides-Extra: test
Provides-Extra: types
License-File: LICENSE
